pyqt_svg_button/__init__.py
pyqt_svg_button/svgButton.py
pyqt_svg_button-0.0.26.dist-info/LICENSE
pyqt_svg_button-0.0.26.dist-info/METADATA
pyqt_svg_button-0.0.26.dist-info/WHEEL
pyqt_svg_button-0.0.26.dist-info/top_level.txt
pyqt_svg_button-0.0.26.dist-info/RECORD
