Metadata-Version: 2.1
Name: pyqt-svg-button
Version: 0.0.26
Summary: PyQt button which supports svg icon (not a fake low quality svg icon)
Home-page: https://github.com/yjg30737/pyqt-svg-button.git
Author: Jung Gyu Yoon
Author-email: yjg30737@gmail.com
License: MIT
Platform: UNKNOWN
License-File: LICENSE
Requires-Dist: PyQt5 (>=5.8)
Requires-Dist: pyqt-svg-abstractbutton (>=0.0.1)
